{
    "ReRoutes": [
      {
        "DownstreamPathTemplate": "/api/user/{all}",
        "DownstreamScheme": "http",
        "DownstreamHostAndPorts": [
          {
            "Host": "localhost",
            "Port": 56688
          }
        ],
        "UpstreamPathTemplate": "/user/{all}",
        "UpstreamHttpMethod": [ "Get" ],
        "AuthenticationOptions": {
          "AuthenticationProviderKey": "TestKey",
          "AllowedScopes": []
        },
        "RouteClaimsRequirement": {
          "UserType": "registered"
        }
      }

    ]
}